gst.py
gst-0.1.13.dist-info/LICENSE.md
gst-0.1.13.dist-info/METADATA
gst-0.1.13.dist-info/WHEEL
gst-0.1.13.dist-info/entry_points.txt
gst-0.1.13.dist-info/top_level.txt
gst-0.1.13.dist-info/RECORD
