Metadata-Version: 2.1
Name: gst
Version: 0.1.13
Summary: Git status tool
Home-page: https://github.com/cpagravel/gst-python
Author: Chris Gravel
Author-email: Chris Gravel <cpagravel@gmail.com>
License: MIT
Project-URL: Homepage, https://github.com/cpagravel/gst-python
Project-URL: Repository, https://github.com/cpagravel/gst-python
Project-URL: Download, https://github.com/cpagravel/gst-python/archive/0.1.13.tar.gz
Keywords: git,git status,git workflow
Classifier: Development Status :: 4 - Beta
Classifier: Intended Audience :: Developers
Classifier: Topic :: Software Development :: Version Control :: Git
Classifier: Programming Language :: Python :: 3
Classifier: Programming Language :: Python :: 3.6
Classifier: Programming Language :: Python :: 3.7
Classifier: Programming Language :: Python :: 3.8
Classifier: Programming Language :: Python :: 3.9
Classifier: Programming Language :: Python :: 3.10
Classifier: Programming Language :: Python :: 3.11
Classifier: Programming Language :: Python :: 3.12
Requires-Python: >=3.6
License-File: LICENSE.md
